TOPSIS/__init__.py
TOPSIS/__main__.py
Topsis_Samarth_101903793-1.0.0.dist-info/LICENSE
Topsis_Samarth_101903793-1.0.0.dist-info/METADATA
Topsis_Samarth_101903793-1.0.0.dist-info/WHEEL
Topsis_Samarth_101903793-1.0.0.dist-info/entry_points.txt
Topsis_Samarth_101903793-1.0.0.dist-info/top_level.txt
Topsis_Samarth_101903793-1.0.0.dist-info/RECORD
