Metadata-Version: 2.1
Name: Topsis-Samarth-101903793
Version: 1.0.0
Summary: Calculate TOPSIS Ranks
Author: Samarth Varshney
Author-email: svarshney_be19@thapar.edu
License: MIT
Platform: UNKNOWN
Classifier: License :: OSI Approved :: MIT License
Classifier: Programming Language :: Python :: 3.6
Classifier: Programming Language :: Python :: 3.7
Classifier: Programming Language :: Python :: 3.8
License-File: LICENSE
